lsst/__init__.py
lsst/daf/__init__.py
lsst/daf/relation/__init__.py
lsst/daf/relation/_binary_operation.py
lsst/daf/relation/_diagnostics.py
lsst/daf/relation/_engine.py
lsst/daf/relation/_exceptions.py
lsst/daf/relation/_leaf_relation.py
lsst/daf/relation/_marker_relation.py
lsst/daf/relation/_materialization.py
lsst/daf/relation/_operation_relations.py
lsst/daf/relation/_processor.py
lsst/daf/relation/_relation.py
lsst/daf/relation/_transfer.py
lsst/daf/relation/_unary_operation.py
lsst/daf/relation/py.typed
lsst/daf/relation/tests.py
lsst/daf/relation/version.py
lsst/daf/relation/_columns/__init__.py
lsst/daf/relation/_columns/_container.py
lsst/daf/relation/_columns/_expression.py
lsst/daf/relation/_columns/_predicate.py
lsst/daf/relation/_columns/_tag.py
lsst/daf/relation/_operations/__init__.py
lsst/daf/relation/_operations/_calculation.py
lsst/daf/relation/_operations/_chain.py
lsst/daf/relation/_operations/_deduplication.py
lsst/daf/relation/_operations/_join.py
lsst/daf/relation/_operations/_projection.py
lsst/daf/relation/_operations/_selection.py
lsst/daf/relation/_operations/_slice.py
lsst/daf/relation/_operations/_sort.py
lsst/daf/relation/iteration/__init__.py
lsst/daf/relation/iteration/_engine.py
lsst/daf/relation/iteration/_row_iterable.py
lsst/daf/relation/sql/__init__.py
lsst/daf/relation/sql/_engine.py
lsst/daf/relation/sql/_payload.py
lsst/daf/relation/sql/_select.py
lsst_daf_relation-29.2025.4500.dist-info/licenses/COPYRIGHT
lsst_daf_relation-29.2025.4500.dist-info/licenses/LICENSE
lsst_daf_relation-29.2025.4500.dist-info/METADATA
lsst_daf_relation-29.2025.4500.dist-info/WHEEL
lsst_daf_relation-29.2025.4500.dist-info/top_level.txt
lsst_daf_relation-29.2025.4500.dist-info/zip-safe
lsst_daf_relation-29.2025.4500.dist-info/RECORD
